gguf_coder/__init__.py
gguf_coder/__main__.py
gguf_coder-0.0.6.dist-info/LICENSE
gguf_coder-0.0.6.dist-info/WHEEL
gguf_coder-0.0.6.dist-info/METADATA
gguf_coder-0.0.6.dist-info/RECORD
