Metadata-Version: 2.1
Name: gguf-coder
Version: 0.0.6
Summary: GGUF coder
Author-email: gguf <info@gguf.us>
Classifier: License :: OSI Approved :: MIT License
Project-URL: Issues, https://github.com/calcuis/gguf-coder/issues
Project-URL: Repository, https://github.com/calcuis/gguf-coder
